x_twitter_mcp/__init__.py
x_twitter_mcp/server.py
x_twitter_mcp-0.1.11.dist-info/METADATA
x_twitter_mcp-0.1.11.dist-info/WHEEL
x_twitter_mcp-0.1.11.dist-info/entry_points.txt
x_twitter_mcp-0.1.11.dist-info/licenses/LICENSE
x_twitter_mcp-0.1.11.dist-info/RECORD
