Metadata-Version: 2.4
Name: x-twitter-mcp
Version: 0.1.11
Summary: Twitter search tool for FastMCP using Tweepy
Project-URL: Homepage, https://github.com/rafaljanicki/x-twitter-mcp-server
Project-URL: Issues, https://github.com/rafaljanicki/x-twitter-mcp-server/issues
Author-email: Rafal Janicki <rafal@kult.io>
License-Expression: MIT
License-File: LICENSE
Classifier: License :: OSI Approved :: MIT License
Classifier: Operating System :: OS Independent
Classifier: Programming Language :: Python :: 3
Classifier: Programming Language :: Python :: 3.10
Classifier: Programming Language :: Python :: 3.11
Classifier: Programming Language :: Python :: 3.12
Classifier: Programming Language :: Python :: 3.13
Requires-Python: >=3.10
Requires-Dist: fastmcp>=2.2.0
Requires-Dist: python-dotenv>=0.21.0
Requires-Dist: tweepy>=4.15.0
